{
    "m_Version": 12,
    "DisplayName": "#STR_EXPANSION_MARKET_CATEGORY_ASSAULT_RIFLES",
    "Icon": "Deliver",
    "Color": "FBFCFEFF",
    "IsExchange": 0,
    "InitStockPercent": -1,
    "Items": [
        {
            "ClassName": "BO_AN94",
            "MaxPriceThreshold": 75000,
            "MinPriceThreshold": 75000,
            "SellPricePercent": -1.0,
            "MaxStockThreshold": 1,
            "MinStockThreshold": 1,
            "QuantityPercent": -1,
            "SpawnAttachments": [
            ],
            "Variants": []
        },
        {
            "ClassName": "BO_RPK16",
            "MaxPriceThreshold": 75000,
            "MinPriceThreshold": 75000,
            "SellPricePercent": -1.0,
            "MaxStockThreshold": 1,
            "MinStockThreshold": 1,
            "QuantityPercent": -1,
            "SpawnAttachments": [
            ],
            "Variants": []
        },
        {
            "ClassName": "BO_U100",
            "MaxPriceThreshold": 75000,
            "MinPriceThreshold": 75000,
            "SellPricePercent": -1.0,
            "MaxStockThreshold": 1,
            "MinStockThreshold": 1,
            "QuantityPercent": -1,
            "SpawnAttachments": [
            ],
            "Variants": []
        },
        {
            "ClassName": "BO_G36C",
            "MaxPriceThreshold": 75000,
            "MinPriceThreshold": 75000,
            "SellPricePercent": -1.0,
            "MaxStockThreshold": 1,
            "MinStockThreshold": 1,
            "QuantityPercent": -1,
            "SpawnAttachments": [
            ],
            "Variants": []
        },
        {
            "ClassName": "BO_G36A1",
            "MaxPriceThreshold": 75000,
            "MinPriceThreshold": 7500,
            "SellPricePercent": -1.0,
            "MaxStockThreshold": 1,
            "MinStockThreshold": 1,
            "QuantityPercent": -1,
            "SpawnAttachments": [
            ],
            "Variants": []
        },
        {
            "ClassName": "BO_M1918",
            "MaxPriceThreshold": 75000,
            "MinPriceThreshold": 7500,
            "SellPricePercent": -1.0,
            "MaxStockThreshold": 1,
            "MinStockThreshold": 1,
            "QuantityPercent": -1,
            "SpawnAttachments": [
                "BO_Mag_M1918_20rnd"
            ],
            "Variants": []
        },
        {
            "ClassName": "BO_M1941",
            "MaxPriceThreshold": 75000,
            "MinPriceThreshold": 7500,
            "SellPricePercent": -1.0,
            "MaxStockThreshold": 1,
            "MinStockThreshold": 1,
            "QuantityPercent": -1,
            "SpawnAttachments": [
            ],
            "Variants": []
        },
        {
            "ClassName": "BO_SA58",
            "MaxPriceThreshold": 75000,
            "MinPriceThreshold": 75000,
            "SellPricePercent": -1.0,
            "MaxStockThreshold": 1,
            "MinStockThreshold": 1,
            "QuantityPercent": -1,
            "SpawnAttachments": [
                ""
            ],
            "Variants": []
        },
        {
            "ClassName": "BO_PDWR_556",
            "MaxPriceThreshold": 75000,
            "MinPriceThreshold": 75000,
            "SellPricePercent": -1.0,
            "MaxStockThreshold": 1,
            "MinStockThreshold": 1,
            "QuantityPercent": -1,
            "SpawnAttachments": [
                ""
            ],
            "Variants": []
        },
        {
            "ClassName": "BO_ACR_Tan",
            "MaxPriceThreshold": 75000,
            "MinPriceThreshold": 75000,
            "SellPricePercent": -1.0,
            "MaxStockThreshold": 1,
            "MinStockThreshold": 1,
            "QuantityPercent": -1,
            "SpawnAttachments": [
                ""
            ],
            "Variants": [
			    "BO_ACR_Black",
				"BO_ACR_ODGreen"
			]
        },
        {
            "ClassName": "BO_AR15",
            "MaxPriceThreshold": 75000,
            "MinPriceThreshold": 75000,
            "SellPricePercent": -1.0,
            "MaxStockThreshold": 1,
            "MinStockThreshold": 1,
            "QuantityPercent": -1,
            "SpawnAttachments": [
                ""
            ],
            "Variants": []
        },
        {
            "ClassName": "BO_FNFAL",
            "MaxPriceThreshold": 75000,
            "MinPriceThreshold": 75000,
            "SellPricePercent": -1.0,
            "MaxStockThreshold": 1,
            "MinStockThreshold": 1,
            "QuantityPercent": -1,
            "SpawnAttachments": [
                ""
            ],
            "Variants": []
        },
        {
            "ClassName": "BO_HK416",
            "MaxPriceThreshold": 75000,
            "MinPriceThreshold": 75000,
            "SellPricePercent": -1.0,
            "MaxStockThreshold": 1,
            "MinStockThreshold": 1,
            "QuantityPercent": -1,
            "SpawnAttachments": [
                ""
            ],
            "Variants": []
        },
        {
            "ClassName": "BO_SCARL_Black",
            "MaxPriceThreshold": 75000,
            "MinPriceThreshold": 75000,
            "SellPricePercent": -1.0,
            "MaxStockThreshold": 1,
            "MinStockThreshold": 1,
            "QuantityPercent": -1,
            "SpawnAttachments": [
                ""
            ],
            "Variants": [
                "BO_SCARL_Tan"
            ]
        },
        {
            "ClassName": "BO_SCARH_Black",
            "MaxPriceThreshold": 75000,
            "MinPriceThreshold": 75000,
            "SellPricePercent": -1.0,
            "MaxStockThreshold": 1,
            "MinStockThreshold": 1,
            "QuantityPercent": -1,
            "SpawnAttachments": [
                ""
            ],
            "Variants": [
                "BO_SCARH_Tan"
            ]
        },
        {
            "ClassName": "BO_Sig552",
            "MaxPriceThreshold": 75000,
            "MinPriceThreshold": 75000,
            "SellPricePercent": -1.0,
            "MaxStockThreshold": 1,
            "MinStockThreshold": 1,
            "QuantityPercent": -1,
            "SpawnAttachments": [
                ""
            ],
            "Variants": []
        },
        {
            "ClassName": "BO_AK5C",
            "MaxPriceThreshold": 75000,
            "MinPriceThreshold": 75000,
            "SellPricePercent": -1.0,
            "MaxStockThreshold": 1,
            "MinStockThreshold": 1,
            "QuantityPercent": -1,
            "SpawnAttachments": [
                ""
            ],
            "Variants": []
        },
        {
            "ClassName": "BO_Groza_762",
            "MaxPriceThreshold": 75000,
            "MinPriceThreshold": 75000,
            "SellPricePercent": -1.0,
            "MaxStockThreshold": 1,
            "MinStockThreshold": 1,
            "QuantityPercent": -1,
            "SpawnAttachments": [
                ""
            ],
            "Variants": []
        },
        {
            "ClassName": "BO_Groza_9x39",
            "MaxPriceThreshold": 75000,
            "MinPriceThreshold": 75000,
            "SellPricePercent": -1.0,
            "MaxStockThreshold": 1,
            "MinStockThreshold": 1,
            "QuantityPercent": -1,
            "SpawnAttachments": [
                ""
            ],
            "Variants": []
        },
        {
            "ClassName": "BO_FAMAS",
            "MaxPriceThreshold": 75000,
            "MinPriceThreshold": 75000,
            "SellPricePercent": -1.0,
            "MaxStockThreshold": 1,
            "MinStockThreshold": 1,
            "QuantityPercent": -1,
            "SpawnAttachments": [
                ""
            ],
            "Variants": []
        },
        {
            "ClassName": "BO_ASVAL",
            "MaxPriceThreshold": 75000,
            "MinPriceThreshold": 75000,
            "SellPricePercent": -1.0,
            "MaxStockThreshold": 1,
            "MinStockThreshold": 1,
            "QuantityPercent": -1,
            "SpawnAttachments": [
                "BO_Mag_ASVAL_30rnd"
            ],
            "Variants": []
        },
        {
            "ClassName": "BO_AK74",
            "MaxPriceThreshold": 75000,
            "MinPriceThreshold": 75000,
            "SellPricePercent": -1.0,
            "MaxStockThreshold": 1,
            "MinStockThreshold": 1,
            "QuantityPercent": -1,
            "SpawnAttachments": [
                "BO_AK74_30rnd"
            ],
            "Variants": []
        },
        {
            "ClassName": "BO_AKM",
            "MaxPriceThreshold": 75000,
            "MinPriceThreshold": 75000,
            "SellPricePercent": -1.0,
            "MaxStockThreshold": 1,
            "MinStockThreshold": 1,
            "QuantityPercent": -1,
            "SpawnAttachments": [
                "BO_PMAG_AKM_30rnd",
                "BO_PMAG_AKM_30rnd_FDE"
            ],
            "Variants": [
                "BO_AKM_FDE"
            ]
        },
        {
            "ClassName": "BO_ARX160",
            "MaxPriceThreshold": 75000,
            "MinPriceThreshold": 75000,
            "SellPricePercent": -1.0,
            "MaxStockThreshold": 1,
            "MinStockThreshold": 1,
            "QuantityPercent": -1,
            "SpawnAttachments": [
                ""
            ],
            "Variants": []
        },
        {
            "ClassName": "BO_G3A3",
            "MaxPriceThreshold": 75000,
            "MinPriceThreshold": 75000,
            "SellPricePercent": -1.0,
            "MaxStockThreshold": 1,
            "MinStockThreshold": 1,
            "QuantityPercent": -1,
            "SpawnAttachments": [
                "BO_Mag_G3A3_20rnd"
            ],
            "Variants": []
        },
        {
            "ClassName": "BO_HoneyBadger",
            "MaxPriceThreshold": 75000,
            "MinPriceThreshold": 75000,
            "SellPricePercent": -1.0,
            "MaxStockThreshold": 1,
            "MinStockThreshold": 1,
            "QuantityPercent": -1,
            "SpawnAttachments": [
                ""
            ],
            "Variants": []
        },
        {
            "ClassName": "BO_M16A4",
            "MaxPriceThreshold": 75000,
            "MinPriceThreshold": 75000,
            "SellPricePercent": -1.0,
            "MaxStockThreshold": 1,
            "MinStockThreshold": 1,
            "QuantityPercent": -1,
            "SpawnAttachments": [
                ""
            ],
            "Variants": []
        },
        {
            "ClassName": "BO_TAR21",
            "MaxPriceThreshold": 75000,
            "MinPriceThreshold": 75000,
            "SellPricePercent": -1.0,
            "MaxStockThreshold": 1,
            "MinStockThreshold": 1,
            "QuantityPercent": -1,
            "SpawnAttachments": [
                ""
            ],
            "Variants": []
        },
        {
            "ClassName": "BO_MDR_Black",
            "MaxPriceThreshold": 75000,
            "MinPriceThreshold": 75000,
            "SellPricePercent": -1.0,
            "MaxStockThreshold": 1,
            "MinStockThreshold": 1,
            "QuantityPercent": -1,
            "SpawnAttachments": [
                ""
            ],
            "Variants": [
                "BO_MDR_Tan"
            ]
        },
        {
            "ClassName": "BO_AUGA1",
            "MaxPriceThreshold": 75000,
            "MinPriceThreshold": 75000,
            "SellPricePercent": -1.0,
            "MaxStockThreshold": 1,
            "MinStockThreshold": 1,
            "QuantityPercent": -1,
            "SpawnAttachments": [
                ""
            ],
            "Variants": []
        },
        {
            "ClassName": "BO_MCXSpear_Tan",
            "MaxPriceThreshold": 75000,
            "MinPriceThreshold": 75000,
            "SellPricePercent": -1.0,
            "MaxStockThreshold": 1,
            "MinStockThreshold": 1,
            "QuantityPercent": -1,
            "SpawnAttachments": [
                "BO_Mag_MCXSpear_20rnd",
                "BO_MCXSpear_Bttstck_Tan"
            ],
            "Variants": []
        },
        {
            "ClassName": "BO_M16A1",
            "MaxPriceThreshold": 75000,
            "MinPriceThreshold": 7500,
            "SellPricePercent": -1.0,
            "MaxStockThreshold": 1,
            "MinStockThreshold": 1,
            "QuantityPercent": -1,
            "SpawnAttachments": [
                ""
            ],
            "Variants": []
        },
        {
            "ClassName": "BO_AEK971",
            "MaxPriceThreshold": 75000,
            "MinPriceThreshold": 75000,
            "SellPricePercent": -1.0,
            "MaxStockThreshold": 1,
            "MinStockThreshold": 1,
            "QuantityPercent": -1,
            "SpawnAttachments": [
                ""
            ],
            "Variants": []
        }
    ]
}